tests/__init__.py
tests/test_data_ingress.py
vespr_model_deployment_utils/__init__.py
vespr_model_deployment_utils/config.py
vespr_model_deployment_utils/data_ingress.py
vespr_model_deployment_utils-2.4.2.dist-info/METADATA
vespr_model_deployment_utils-2.4.2.dist-info/WHEEL
vespr_model_deployment_utils-2.4.2.dist-info/top_level.txt
vespr_model_deployment_utils-2.4.2.dist-info/RECORD
