Metadata-Version: 2.1
Name: vespr-model-deployment-utils
Version: 2.4.2
Summary: VESPR Data Processing Utilities Package
Home-page: https://gitlab.com/CalypsoAI/vespr-model-deployment-utils
Author: Calypso AI
License: UNKNOWN
Platform: UNKNOWN
Classifier: Programming Language :: Python :: 3
Classifier: License :: OSI Approved :: MIT License
Classifier: Operating System :: OS Independent
Requires-Python: >=3.8
Requires-Dist: numpy (>=1.18.1)
Requires-Dist: pandas (==1.2.5)
Requires-Dist: scikit-learn (==0.23.2)
